parinya/DHT11.py
parinya/DHT22.py
parinya/LINE.py
parinya/__init__.py
parinya/pi.py
parinya/stock.py
parinya/yolov3.py
parinya/yolov4.py
parinya-0.0.32.dist-info/LICENSE
parinya-0.0.32.dist-info/METADATA
parinya-0.0.32.dist-info/WHEEL
parinya-0.0.32.dist-info/top_level.txt
parinya-0.0.32.dist-info/RECORD
