Metadata-Version: 2.1
Name: parinya
Version: 0.0.32
Summary: A collection of my codes
Home-page: UNKNOWN
Author: Parinya Sanguansat
Author-email: sanguansat@yahoo.com
License: UNKNOWN
Platform: UNKNOWN
Classifier: Programming Language :: Python :: 3
Classifier: License :: OSI Approved :: MIT License
Classifier: Operating System :: OS Independent
License-File: LICENSE
Requires-Dist: Pillow
Requires-Dist: requests
Requires-Dist: numpy
Requires-Dist: matplotlib
